langchain_opensearch/__init__.py
langchain_opensearch/client.py
langchain_opensearch/retrievers.py
langchain_opensearch/vectorstores.py
langchain_opensearch-0.0.2.dist-info/LICENSE
langchain_opensearch-0.0.2.dist-info/METADATA
langchain_opensearch-0.0.2.dist-info/WHEEL
langchain_opensearch-0.0.2.dist-info/RECORD
