Metadata-Version: 2.1
Name: langchain-opensearch
Version: 0.0.2
Summary: An integration package connecting Opensearch and LangChain
License: MIT
Author: 강재호
Author-email: greennuri@gmail.com
Requires-Python: >=3.9,<4.0
Classifier: License :: OSI Approved :: MIT License
Classifier: Programming Language :: Python :: 3
Classifier: Programming Language :: Python :: 3.9
Classifier: Programming Language :: Python :: 3.10
Classifier: Programming Language :: Python :: 3.11
Classifier: Programming Language :: Python :: 3.12
Requires-Dist: langchain-community (>=0.3.0,<0.4.0)
Requires-Dist: langchain-core (>=0.3.5,<0.4.0)
Requires-Dist: langchain-text-splitters (>=0.3.0,<0.4.0)
Requires-Dist: opensearch-py (>=2.7.0)
Requires-Dist: setuptools (>=75.1.0,<76.0.0)
